{
  "_fv": 24,
  "_type": "potion",
  "definition": {
    "potionName": "Potion of Sneaking",
    "splashName": "Splash Potion of Sneaking",
    "lingeringName": "Lingering Potion of Sneaking",
    "arrowName": "Arrow of Potion of Sneaking",
    "effects": [
      {
        "effect": {
          "value": "INVISIBILITY"
        },
        "duration": 3600,
        "amplifier": 3,
        "ambient": false,
        "showParticles": false
      },
      {
        "effect": {
          "value": "WEAKNESS"
        },
        "duration": 3600,
        "amplifier": 1,
        "ambient": false,
        "showParticles": false
      },
      {
        "effect": {
          "value": "SPEED"
        },
        "duration": 3600,
        "amplifier": 2,
        "ambient": false,
        "showParticles": false
      },
      {
        "effect": {
          "value": "NIGHT_VISION"
        },
        "duration": 3600,
        "amplifier": 100,
        "ambient": false,
        "showParticles": false
      },
      {
        "effect": {
          "value": "JUMP_BOOST"
        },
        "duration": 3600,
        "amplifier": 2,
        "ambient": false,
        "showParticles": false
      }
    ]
  }
}